example_pkg/__init__.py
example_pkg/timer.py
func_timer-0.0.1.dist-info/LICENSE
func_timer-0.0.1.dist-info/METADATA
func_timer-0.0.1.dist-info/WHEEL
func_timer-0.0.1.dist-info/top_level.txt
func_timer-0.0.1.dist-info/RECORD
