Metadata-Version: 2.1
Name: func-timer
Version: 0.0.1
Summary: A small example package, used for timing function
Home-page: https://github.com/zqsc
Author: zqsc
Author-email: zhao_zqsc@sina.com
License: UNKNOWN
Platform: UNKNOWN
Classifier: Programming Language :: Python :: 3
Classifier: License :: OSI Approved :: MIT License
Classifier: Operating System :: OS Independent
Requires-Python: >=3.6
